README.md
setup.py
ray/__init__.py
ray/ray.py
rayuwu.egg-info/PKG-INFO
rayuwu.egg-info/SOURCES.txt
rayuwu.egg-info/dependency_links.txt
rayuwu.egg-info/requires.txt
rayuwu.egg-info/top_level.txt