Metadata-Version: 2.1
Name: rayuwu
Version: 1.1.4
Summary: A package to interact with Discord API
Home-page: https://github.com/theabsoluteray/ray-wrapper
Author: ray
Author-email: me.harshu.yt.04@gmail.com
Classifier: Programming Language :: Python :: 3
Classifier: License :: OSI Approved :: MIT License
Classifier: Operating System :: OS Independent
Requires-Dist: requests
